sum_04869/__init__.py
sum_04869-0.0.1.dist-info/LICENSE.txt
sum_04869-0.0.1.dist-info/METADATA
sum_04869-0.0.1.dist-info/WHEEL
sum_04869-0.0.1.dist-info/top_level.txt
sum_04869-0.0.1.dist-info/RECORD
